gnomix/__init__.py
gnomix/generate_dataset_from_1kg.py
gnomix/laidataset.py
gnomix/paths.py
gnomix/postprocess.py
gnomix/preprocess.py
gnomix/utils.py
gnomix/visualization.py
gnomix-0.0.7.dist-info/LICENSE.md
gnomix-0.0.7.dist-info/METADATA
gnomix-0.0.7.dist-info/WHEEL
gnomix-0.0.7.dist-info/top_level.txt
gnomix-0.0.7.dist-info/RECORD
