Metadata-Version: 2.1
Name: gnomix
Version: 0.0.7
Summary: A fast, scalable, and accurate local ancestry method
Home-page: https://github.com/AI-sandbox/gnomix
Author: Helgi Hilmarsson & Arvind Kumar
Author-email: helgi37@gmail.com
License: UNKNOWN
Project-URL: Bug Tracker, https://github.com/AI-sandbox/gnomix/issues
Platform: UNKNOWN
Classifier: Programming Language :: Python :: 3
Classifier: License :: Free for non-commercial use
Classifier: Operating System :: OS Independent
Requires-Python: >=3.6
License-File: LICENSE.md
